{"nodes": [{"id": "d_business_code_smartopd_smartopd_backend_src_operations_crm_dto_record_consumption_dto_ts", "label": "record-consumption.dto.ts", "file_type": "code", "source_file": "D:\\Business\\Code\\SmartOPD\\smartopd-backend\\src\\operations-crm\\dto\\record-consumption.dto.ts", "source_location": "L1"}, {"id": "record_consumption_dto_recordconsumptiondto", "label": "RecordConsumptionDto", "file_type": "code", "source_file": "D:\\Business\\Code\\SmartOPD\\smartopd-backend\\src\\operations-crm\\dto\\record-consumption.dto.ts", "source_location": "L4"}], "edges": [{"source": "d_business_code_smartopd_smartopd_backend_src_operations_crm_dto_record_consumption_dto_ts", "target": "class_validator", "relation": "imports_from", "confidence": "EXTRACTED", "source_file": "D:\\Business\\Code\\SmartOPD\\smartopd-backend\\src\\operations-crm\\dto\\record-consumption.dto.ts", "source_location": "L1", "weight": 1.0}, {"source": "d_business_code_smartopd_smartopd_backend_src_operations_crm_dto_record_consumption_dto_ts", "target": "swagger", "relation": "imports_from", "confidence": "EXTRACTED", "source_file": "D:\\Business\\Code\\SmartOPD\\smartopd-backend\\src\\operations-crm\\dto\\record-consumption.dto.ts", "source_location": "L2", "weight": 1.0}, {"source": "d_business_code_smartopd_smartopd_backend_src_operations_crm_dto_record_consumption_dto_ts", "target": "record_consumption_dto_recordconsumptiondto", "relation": "contains", "confidence": "EXTRACTED", "source_file": "D:\\Business\\Code\\SmartOPD\\smartopd-backend\\src\\operations-crm\\dto\\record-consumption.dto.ts", "source_location": "L4", "weight": 1.0}], "raw_calls": []}