{"nodes": [{"id": "d_business_code_smartopd_smartopd_backend_src_pharmacy_pharmacy_service_ts", "label": "pharmacy.service.ts", "file_type": "code", "source_file": "D:\\Business\\Code\\SmartOPD\\smartopd-backend\\src\\pharmacy\\pharmacy.service.ts", "source_location": "L1"}, {"id": "pharmacy_service_pharmacyservice", "label": "PharmacyService", "file_type": "code", "source_file": "D:\\Business\\Code\\SmartOPD\\smartopd-backend\\src\\pharmacy\\pharmacy.service.ts", "source_location": "L18"}, {"id": "pharmacy_service_pharmacyservice_constructor", "label": ".constructor()", "file_type": "code", "source_file": "D:\\Business\\Code\\SmartOPD\\smartopd-backend\\src\\pharmacy\\pharmacy.service.ts", "source_location": "L19"}, {"id": "pharmacy_service_pharmacyservice_getdispensequeue", "label": ".getDispenseQueue()", "file_type": "code", "source_file": "D:\\Business\\Code\\SmartOPD\\smartopd-backend\\src\\pharmacy\\pharmacy.service.ts", "source_location": "L30"}, {"id": "pharmacy_service_pharmacyservice_dispense", "label": ".dispense()", "file_type": "code", "source_file": "D:\\Business\\Code\\SmartOPD\\smartopd-backend\\src\\pharmacy\\pharmacy.service.ts", "source_location": "L38"}, {"id": "pharmacy_service_pharmacyservice_checkallergy", "label": ".checkAllergy()", "file_type": "code", "source_file": "D:\\Business\\Code\\SmartOPD\\smartopd-backend\\src\\pharmacy\\pharmacy.service.ts", "source_location": "L64"}, {"id": "pharmacy_service_pharmacyservice_checkdruginteractions", "label": ".checkDrugInteractions()", "file_type": "code", "source_file": "D:\\Business\\Code\\SmartOPD\\smartopd-backend\\src\\pharmacy\\pharmacy.service.ts", "source_location": "L117"}, {"id": "pharmacy_service_pharmacyservice_getinventory", "label": ".getInventory()", "file_type": "code", "source_file": "D:\\Business\\Code\\SmartOPD\\smartopd-backend\\src\\pharmacy\\pharmacy.service.ts", "source_location": "L187"}, {"id": "pharmacy_service_pharmacyservice_addinventory", "label": ".addInventory()", "file_type": "code", "source_file": "D:\\Business\\Code\\SmartOPD\\smartopd-backend\\src\\pharmacy\\pharmacy.service.ts", "source_location": "L204"}, {"id": "pharmacy_service_pharmacyservice_getlowstock", "label": ".getLowStock()", "file_type": "code", "source_file": "D:\\Business\\Code\\SmartOPD\\smartopd-backend\\src\\pharmacy\\pharmacy.service.ts", "source_location": "L228"}, {"id": "pharmacy_service_pharmacyservice_getexpiringstock", "label": ".getExpiringStock()", "file_type": "code", "source_file": "D:\\Business\\Code\\SmartOPD\\smartopd-backend\\src\\pharmacy\\pharmacy.service.ts", "source_location": "L238"}, {"id": "pharmacy_service_pharmacyservice_getdispensehistory", "label": ".getDispenseHistory()", "file_type": "code", "source_file": "D:\\Business\\Code\\SmartOPD\\smartopd-backend\\src\\pharmacy\\pharmacy.service.ts", "source_location": "L255"}], "edges": [{"source": "d_business_code_smartopd_smartopd_backend_src_pharmacy_pharmacy_service_ts", "target": "common", "relation": "imports_from", "confidence": "EXTRACTED", "source_file": "D:\\Business\\Code\\SmartOPD\\smartopd-backend\\src\\pharmacy\\pharmacy.service.ts", "source_location": "L1", "weight": 1.0}, {"source": "d_business_code_smartopd_smartopd_backend_src_pharmacy_pharmacy_service_ts", "target": "typeorm", "relation": "imports_from", "confidence": "EXTRACTED", "source_file": "D:\\Business\\Code\\SmartOPD\\smartopd-backend\\src\\pharmacy\\pharmacy.service.ts", "source_location": "L6", "weight": 1.0}, {"source": "d_business_code_smartopd_smartopd_backend_src_pharmacy_pharmacy_service_ts", "target": "typeorm", "relation": "imports_from", "confidence": "EXTRACTED", "source_file": "D:\\Business\\Code\\SmartOPD\\smartopd-backend\\src\\pharmacy\\pharmacy.service.ts", "source_location": "L7", "weight": 1.0}, {"source": "d_business_code_smartopd_smartopd_backend_src_pharmacy_pharmacy_service_ts", "target": "axios", "relation": "imports_from", "confidence": "EXTRACTED", "source_file": "D:\\Business\\Code\\SmartOPD\\smartopd-backend\\src\\pharmacy\\pharmacy.service.ts", "source_location": "L8", "weight": 1.0}, {"source": "d_business_code_smartopd_smartopd_backend_src_pharmacy_pharmacy_service_ts", "target": "config", "relation": "imports_from", "confidence": "EXTRACTED", "source_file": "D:\\Business\\Code\\SmartOPD\\smartopd-backend\\src\\pharmacy\\pharmacy.service.ts", "source_location": "L9", "weight": 1.0}, {"source": "d_business_code_smartopd_smartopd_backend_src_pharmacy_pharmacy_service_ts", "target": "rxjs", "relation": "imports_from", "confidence": "EXTRACTED", "source_file": "D:\\Business\\Code\\SmartOPD\\smartopd-backend\\src\\pharmacy\\pharmacy.service.ts", "source_location": "L10", "weight": 1.0}, {"source": "d_business_code_smartopd_smartopd_backend_src_pharmacy_pharmacy_service_ts", "target": "d_business_code_smartopd_smartopd_backend_src_pharmacy_entities_dispense_record_entity", "relation": "imports_from", "confidence": "EXTRACTED", "source_file": "D:\\Business\\Code\\SmartOPD\\smartopd-backend\\src\\pharmacy\\pharmacy.service.ts", "source_location": "L11", "weight": 1.0}, {"source": "d_business_code_smartopd_smartopd_backend_src_pharmacy_pharmacy_service_ts", "target": "d_business_code_smartopd_smartopd_backend_src_pharmacy_entities_pharmacy_inventory_entity", "relation": "imports_from", "confidence": "EXTRACTED", "source_file": "D:\\Business\\Code\\SmartOPD\\smartopd-backend\\src\\pharmacy\\pharmacy.service.ts", "source_location": "L12", "weight": 1.0}, {"source": "d_business_code_smartopd_smartopd_backend_src_pharmacy_pharmacy_service_ts", "target": "d_business_code_smartopd_smartopd_backend_src_patients_entities_patient_entity", "relation": "imports_from", "confidence": "EXTRACTED", "source_file": "D:\\Business\\Code\\SmartOPD\\smartopd-backend\\src\\pharmacy\\pharmacy.service.ts", "source_location": "L13", "weight": 1.0}, {"source": "d_business_code_smartopd_smartopd_backend_src_pharmacy_pharmacy_service_ts", "target": "d_business_code_smartopd_smartopd_backend_src_pharmacy_dto_dispense_dto", "relation": "imports_from", "confidence": "EXTRACTED", "source_file": "D:\\Business\\Code\\SmartOPD\\smartopd-backend\\src\\pharmacy\\pharmacy.service.ts", "source_location": "L14", "weight": 1.0}, {"source": "d_business_code_smartopd_smartopd_backend_src_pharmacy_pharmacy_service_ts", "target": "d_business_code_smartopd_smartopd_backend_src_pharmacy_dto_create_inventory_dto", "relation": "imports_from", "confidence": "EXTRACTED", "source_file": "D:\\Business\\Code\\SmartOPD\\smartopd-backend\\src\\pharmacy\\pharmacy.service.ts", "source_location": "L15", "weight": 1.0}, {"source": "d_business_code_smartopd_smartopd_backend_src_pharmacy_pharmacy_service_ts", "target": "pharmacy_service_pharmacyservice", "relation": "contains", "confidence": "EXTRACTED", "source_file": "D:\\Business\\Code\\SmartOPD\\smartopd-backend\\src\\pharmacy\\pharmacy.service.ts", "source_location": "L18", "weight": 1.0}, {"source": "pharmacy_service_pharmacyservice", "target": "pharmacy_service_pharmacyservice_constructor", "relation": "method", "confidence": "EXTRACTED", "source_file": "D:\\Business\\Code\\SmartOPD\\smartopd-backend\\src\\pharmacy\\pharmacy.service.ts", "source_location": "L19", "weight": 1.0}, {"source": "pharmacy_service_pharmacyservice", "target": "pharmacy_service_pharmacyservice_getdispensequeue", "relation": "method", "confidence": "EXTRACTED", "source_file": "D:\\Business\\Code\\SmartOPD\\smartopd-backend\\src\\pharmacy\\pharmacy.service.ts", "source_location": "L30", "weight": 1.0}, {"source": "pharmacy_service_pharmacyservice", "target": "pharmacy_service_pharmacyservice_dispense", "relation": "method", "confidence": "EXTRACTED", "source_file": "D:\\Business\\Code\\SmartOPD\\smartopd-backend\\src\\pharmacy\\pharmacy.service.ts", "source_location": "L38", "weight": 1.0}, {"source": "pharmacy_service_pharmacyservice", "target": "pharmacy_service_pharmacyservice_checkallergy", "relation": "method", "confidence": "EXTRACTED", "source_file": "D:\\Business\\Code\\SmartOPD\\smartopd-backend\\src\\pharmacy\\pharmacy.service.ts", "source_location": "L64", "weight": 1.0}, {"source": "pharmacy_service_pharmacyservice", "target": "pharmacy_service_pharmacyservice_checkdruginteractions", "relation": "method", "confidence": "EXTRACTED", "source_file": "D:\\Business\\Code\\SmartOPD\\smartopd-backend\\src\\pharmacy\\pharmacy.service.ts", "source_location": "L117", "weight": 1.0}, {"source": "pharmacy_service_pharmacyservice", "target": "pharmacy_service_pharmacyservice_getinventory", "relation": "method", "confidence": "EXTRACTED", "source_file": "D:\\Business\\Code\\SmartOPD\\smartopd-backend\\src\\pharmacy\\pharmacy.service.ts", "source_location": "L187", "weight": 1.0}, {"source": "pharmacy_service_pharmacyservice", "target": "pharmacy_service_pharmacyservice_addinventory", "relation": "method", "confidence": "EXTRACTED", "source_file": "D:\\Business\\Code\\SmartOPD\\smartopd-backend\\src\\pharmacy\\pharmacy.service.ts", "source_location": "L204", "weight": 1.0}, {"source": "pharmacy_service_pharmacyservice", "target": "pharmacy_service_pharmacyservice_getlowstock", "relation": "method", "confidence": "EXTRACTED", "source_file": "D:\\Business\\Code\\SmartOPD\\smartopd-backend\\src\\pharmacy\\pharmacy.service.ts", "source_location": "L228", "weight": 1.0}, {"source": "pharmacy_service_pharmacyservice", "target": "pharmacy_service_pharmacyservice_getexpiringstock", "relation": "method", "confidence": "EXTRACTED", "source_file": "D:\\Business\\Code\\SmartOPD\\smartopd-backend\\src\\pharmacy\\pharmacy.service.ts", "source_location": "L238", "weight": 1.0}, {"source": "pharmacy_service_pharmacyservice", "target": "pharmacy_service_pharmacyservice_getdispensehistory", "relation": "method", "confidence": "EXTRACTED", "source_file": "D:\\Business\\Code\\SmartOPD\\smartopd-backend\\src\\pharmacy\\pharmacy.service.ts", "source_location": "L255", "weight": 1.0}], "raw_calls": [{"caller_nid": "pharmacy_service_pharmacyservice_getdispensequeue", "callee": "getMany", "source_file": "D:\\Business\\Code\\SmartOPD\\smartopd-backend\\src\\pharmacy\\pharmacy.service.ts", "source_location": "L31"}, {"caller_nid": "pharmacy_service_pharmacyservice_getdispensequeue", "callee": "orderBy", "source_file": "D:\\Business\\Code\\SmartOPD\\smartopd-backend\\src\\pharmacy\\pharmacy.service.ts", "source_location": "L31"}, {"caller_nid": "pharmacy_service_pharmacyservice_getdispensequeue", "callee": "where", "source_file": "D:\\Business\\Code\\SmartOPD\\smartopd-backend\\src\\pharmacy\\pharmacy.service.ts", "source_location": "L31"}, {"caller_nid": "pharmacy_service_pharmacyservice_getdispensequeue", "callee": "createQueryBuilder", "source_file": "D:\\Business\\Code\\SmartOPD\\smartopd-backend\\src\\pharmacy\\pharmacy.service.ts", "source_location": "L31"}, {"caller_nid": "pharmacy_service_pharmacyservice_dispense", "callee": "create", "source_file": "D:\\Business\\Code\\SmartOPD\\smartopd-backend\\src\\pharmacy\\pharmacy.service.ts", "source_location": "L48"}, {"caller_nid": "pharmacy_service_pharmacyservice_dispense", "callee": "save", "source_file": "D:\\Business\\Code\\SmartOPD\\smartopd-backend\\src\\pharmacy\\pharmacy.service.ts", "source_location": "L57"}, {"caller_nid": "pharmacy_service_pharmacyservice_checkallergy", "callee": "findOne", "source_file": "D:\\Business\\Code\\SmartOPD\\smartopd-backend\\src\\pharmacy\\pharmacy.service.ts", "source_location": "L73"}, {"caller_nid": "pharmacy_service_pharmacyservice_checkallergy", "callee": "parse", "source_file": "D:\\Business\\Code\\SmartOPD\\smartopd-backend\\src\\pharmacy\\pharmacy.service.ts", "source_location": "L87"}, {"caller_nid": "pharmacy_service_pharmacyservice_checkallergy", "callee": "map", "source_file": "D:\\Business\\Code\\SmartOPD\\smartopd-backend\\src\\pharmacy\\pharmacy.service.ts", "source_location": "L89"}, {"caller_nid": "pharmacy_service_pharmacyservice_checkallergy", "callee": "split", "source_file": "D:\\Business\\Code\\SmartOPD\\smartopd-backend\\src\\pharmacy\\pharmacy.service.ts", "source_location": "L89"}, {"caller_nid": "pharmacy_service_pharmacyservice_checkallergy", "callee": "toLowerCase", "source_file": "D:\\Business\\Code\\SmartOPD\\smartopd-backend\\src\\pharmacy\\pharmacy.service.ts", "source_location": "L94"}, {"caller_nid": "pharmacy_service_pharmacyservice_checkallergy", "callee": "includes", "source_file": "D:\\Business\\Code\\SmartOPD\\smartopd-backend\\src\\pharmacy\\pharmacy.service.ts", "source_location": "L96"}, {"caller_nid": "pharmacy_service_pharmacyservice_checkallergy", "callee": "includes", "source_file": "D:\\Business\\Code\\SmartOPD\\smartopd-backend\\src\\pharmacy\\pharmacy.service.ts", "source_location": "L96"}, {"caller_nid": "pharmacy_service_pharmacyservice_checkallergy", "callee": "push", "source_file": "D:\\Business\\Code\\SmartOPD\\smartopd-backend\\src\\pharmacy\\pharmacy.service.ts", "source_location": "L97"}, {"caller_nid": "pharmacy_service_pharmacyservice_checkallergy", "callee": "join", "source_file": "D:\\Business\\Code\\SmartOPD\\smartopd-backend\\src\\pharmacy\\pharmacy.service.ts", "source_location": "L108"}, {"caller_nid": "pharmacy_service_pharmacyservice_checkdruginteractions", "callee": "get", "source_file": "D:\\Business\\Code\\SmartOPD\\smartopd-backend\\src\\pharmacy\\pharmacy.service.ts", "source_location": "L147"}, {"caller_nid": "pharmacy_service_pharmacyservice_checkdruginteractions", "callee": "encodeURIComponent", "source_file": "D:\\Business\\Code\\SmartOPD\\smartopd-backend\\src\\pharmacy\\pharmacy.service.ts", "source_location": "L150"}, {"caller_nid": "pharmacy_service_pharmacyservice_checkdruginteractions", "callee": "firstValueFrom", "source_file": "D:\\Business\\Code\\SmartOPD\\smartopd-backend\\src\\pharmacy\\pharmacy.service.ts", "source_location": "L153"}, {"caller_nid": "pharmacy_service_pharmacyservice_checkdruginteractions", "callee": "get", "source_file": "D:\\Business\\Code\\SmartOPD\\smartopd-backend\\src\\pharmacy\\pharmacy.service.ts", "source_location": "L154"}, {"caller_nid": "pharmacy_service_pharmacyservice_checkdruginteractions", "callee": "join", "source_file": "D:\\Business\\Code\\SmartOPD\\smartopd-backend\\src\\pharmacy\\pharmacy.service.ts", "source_location": "L159"}, {"caller_nid": "pharmacy_service_pharmacyservice_checkdruginteractions", "callee": "includes", "source_file": "D:\\Business\\Code\\SmartOPD\\smartopd-backend\\src\\pharmacy\\pharmacy.service.ts", "source_location": "L162"}, {"caller_nid": "pharmacy_service_pharmacyservice_checkdruginteractions", "callee": "toLowerCase", "source_file": "D:\\Business\\Code\\SmartOPD\\smartopd-backend\\src\\pharmacy\\pharmacy.service.ts", "source_location": "L162"}, {"caller_nid": "pharmacy_service_pharmacyservice_checkdruginteractions", "callee": "toLowerCase", "source_file": "D:\\Business\\Code\\SmartOPD\\smartopd-backend\\src\\pharmacy\\pharmacy.service.ts", "source_location": "L162"}, {"caller_nid": "pharmacy_service_pharmacyservice_checkdruginteractions", "callee": "push", "source_file": "D:\\Business\\Code\\SmartOPD\\smartopd-backend\\src\\pharmacy\\pharmacy.service.ts", "source_location": "L163"}, {"caller_nid": "pharmacy_service_pharmacyservice_checkdruginteractions", "callee": "substring", "source_file": "D:\\Business\\Code\\SmartOPD\\smartopd-backend\\src\\pharmacy\\pharmacy.service.ts", "source_location": "L167"}, {"caller_nid": "pharmacy_service_pharmacyservice_getinventory", "callee": "orderBy", "source_file": "D:\\Business\\Code\\SmartOPD\\smartopd-backend\\src\\pharmacy\\pharmacy.service.ts", "source_location": "L191"}, {"caller_nid": "pharmacy_service_pharmacyservice_getinventory", "callee": "andWhere", "source_file": "D:\\Business\\Code\\SmartOPD\\smartopd-backend\\src\\pharmacy\\pharmacy.service.ts", "source_location": "L191"}, {"caller_nid": "pharmacy_service_pharmacyservice_getinventory", "callee": "where", "source_file": "D:\\Business\\Code\\SmartOPD\\smartopd-backend\\src\\pharmacy\\pharmacy.service.ts", "source_location": "L191"}, {"caller_nid": "pharmacy_service_pharmacyservice_getinventory", "callee": "createQueryBuilder", "source_file": "D:\\Business\\Code\\SmartOPD\\smartopd-backend\\src\\pharmacy\\pharmacy.service.ts", "source_location": "L191"}, {"caller_nid": "pharmacy_service_pharmacyservice_getinventory", "callee": "andWhere", "source_file": "D:\\Business\\Code\\SmartOPD\\smartopd-backend\\src\\pharmacy\\pharmacy.service.ts", "source_location": "L198"}, {"caller_nid": "pharmacy_service_pharmacyservice_getinventory", "callee": "getMany", "source_file": "D:\\Business\\Code\\SmartOPD\\smartopd-backend\\src\\pharmacy\\pharmacy.service.ts", "source_location": "L201"}, {"caller_nid": "pharmacy_service_pharmacyservice_addinventory", "callee": "create", "source_file": "D:\\Business\\Code\\SmartOPD\\smartopd-backend\\src\\pharmacy\\pharmacy.service.ts", "source_location": "L208"}, {"caller_nid": "pharmacy_service_pharmacyservice_addinventory", "callee": "now", "source_file": "D:\\Business\\Code\\SmartOPD\\smartopd-backend\\src\\pharmacy\\pharmacy.service.ts", "source_location": "L214"}, {"caller_nid": "pharmacy_service_pharmacyservice_addinventory", "callee": "save", "source_file": "D:\\Business\\Code\\SmartOPD\\smartopd-backend\\src\\pharmacy\\pharmacy.service.ts", "source_location": "L225"}, {"caller_nid": "pharmacy_service_pharmacyservice_getlowstock", "callee": "getMany", "source_file": "D:\\Business\\Code\\SmartOPD\\smartopd-backend\\src\\pharmacy\\pharmacy.service.ts", "source_location": "L229"}, {"caller_nid": "pharmacy_service_pharmacyservice_getlowstock", "callee": "orderBy", "source_file": "D:\\Business\\Code\\SmartOPD\\smartopd-backend\\src\\pharmacy\\pharmacy.service.ts", "source_location": "L229"}, {"caller_nid": "pharmacy_service_pharmacyservice_getlowstock", "callee": "andWhere", "source_file": "D:\\Business\\Code\\SmartOPD\\smartopd-backend\\src\\pharmacy\\pharmacy.service.ts", "source_location": "L229"}, {"caller_nid": "pharmacy_service_pharmacyservice_getlowstock", "callee": "andWhere", "source_file": "D:\\Business\\Code\\SmartOPD\\smartopd-backend\\src\\pharmacy\\pharmacy.service.ts", "source_location": "L229"}, {"caller_nid": "pharmacy_service_pharmacyservice_getlowstock", "callee": "where", "source_file": "D:\\Business\\Code\\SmartOPD\\smartopd-backend\\src\\pharmacy\\pharmacy.service.ts", "source_location": "L229"}, {"caller_nid": "pharmacy_service_pharmacyservice_getlowstock", "callee": "createQueryBuilder", "source_file": "D:\\Business\\Code\\SmartOPD\\smartopd-backend\\src\\pharmacy\\pharmacy.service.ts", "source_location": "L229"}, {"caller_nid": "pharmacy_service_pharmacyservice_getexpiringstock", "callee": "setDate", "source_file": "D:\\Business\\Code\\SmartOPD\\smartopd-backend\\src\\pharmacy\\pharmacy.service.ts", "source_location": "L243"}, {"caller_nid": "pharmacy_service_pharmacyservice_getexpiringstock", "callee": "getDate", "source_file": "D:\\Business\\Code\\SmartOPD\\smartopd-backend\\src\\pharmacy\\pharmacy.service.ts", "source_location": "L243"}, {"caller_nid": "pharmacy_service_pharmacyservice_getexpiringstock", "callee": "find", "source_file": "D:\\Business\\Code\\SmartOPD\\smartopd-backend\\src\\pharmacy\\pharmacy.service.ts", "source_location": "L245"}, {"caller_nid": "pharmacy_service_pharmacyservice_getexpiringstock", "callee": "LessThanOrEqual", "source_file": "D:\\Business\\Code\\SmartOPD\\smartopd-backend\\src\\pharmacy\\pharmacy.service.ts", "source_location": "L249"}, {"caller_nid": "pharmacy_service_pharmacyservice_getdispensehistory", "callee": "orderBy", "source_file": "D:\\Business\\Code\\SmartOPD\\smartopd-backend\\src\\pharmacy\\pharmacy.service.ts", "source_location": "L259"}, {"caller_nid": "pharmacy_service_pharmacyservice_getdispensehistory", "callee": "where", "source_file": "D:\\Business\\Code\\SmartOPD\\smartopd-backend\\src\\pharmacy\\pharmacy.service.ts", "source_location": "L259"}, {"caller_nid": "pharmacy_service_pharmacyservice_getdispensehistory", "callee": "createQueryBuilder", "source_file": "D:\\Business\\Code\\SmartOPD\\smartopd-backend\\src\\pharmacy\\pharmacy.service.ts", "source_location": "L259"}, {"caller_nid": "pharmacy_service_pharmacyservice_getdispensehistory", "callee": "andWhere", "source_file": "D:\\Business\\Code\\SmartOPD\\smartopd-backend\\src\\pharmacy\\pharmacy.service.ts", "source_location": "L265"}, {"caller_nid": "pharmacy_service_pharmacyservice_getdispensehistory", "callee": "andWhere", "source_file": "D:\\Business\\Code\\SmartOPD\\smartopd-backend\\src\\pharmacy\\pharmacy.service.ts", "source_location": "L267"}, {"caller_nid": "pharmacy_service_pharmacyservice_getdispensehistory", "callee": "getMany", "source_file": "D:\\Business\\Code\\SmartOPD\\smartopd-backend\\src\\pharmacy\\pharmacy.service.ts", "source_location": "L271"}]}