{"nodes": [{"id": "d_business_code_smartopd_smartopd_backend_src_admission_entities_admission_entity_ts", "label": "admission.entity.ts", "file_type": "code", "source_file": "D:\\Business\\Code\\SmartOPD\\smartopd-backend\\src\\admission\\entities\\admission.entity.ts", "source_location": "L1"}, {"id": "admission_entity_admission", "label": "Admission", "file_type": "code", "source_file": "D:\\Business\\Code\\SmartOPD\\smartopd-backend\\src\\admission\\entities\\admission.entity.ts", "source_location": "L36"}], "edges": [{"source": "d_business_code_smartopd_smartopd_backend_src_admission_entities_admission_entity_ts", "target": "typeorm", "relation": "imports_from", "confidence": "EXTRACTED", "source_file": "D:\\Business\\Code\\SmartOPD\\smartopd-backend\\src\\admission\\entities\\admission.entity.ts", "source_location": "L1", "weight": 1.0}, {"source": "d_business_code_smartopd_smartopd_backend_src_admission_entities_admission_entity_ts", "target": "admission_entity_admission", "relation": "contains", "confidence": "EXTRACTED", "source_file": "D:\\Business\\Code\\SmartOPD\\smartopd-backend\\src\\admission\\entities\\admission.entity.ts", "source_location": "L36", "weight": 1.0}], "raw_calls": []}