{"nodes": [{"id": "d_business_code_smartopd_smartopd_backend_src_nhcx_dto_nhcx_dto_ts", "label": "nhcx.dto.ts", "file_type": "code", "source_file": "D:\\Business\\Code\\SmartOPD\\smartopd-backend\\src\\nhcx\\dto\\nhcx.dto.ts", "source_location": "L1"}, {"id": "nhcx_dto_createclaimdto", "label": "CreateClaimDto", "file_type": "code", "source_file": "D:\\Business\\Code\\SmartOPD\\smartopd-backend\\src\\nhcx\\dto\\nhcx.dto.ts", "source_location": "L16"}, {"id": "nhcx_dto_updateclaimstatusdto", "label": "UpdateClaimStatusDto", "file_type": "code", "source_file": "D:\\Business\\Code\\SmartOPD\\smartopd-backend\\src\\nhcx\\dto\\nhcx.dto.ts", "source_location": "L61"}, {"id": "nhcx_dto_claimquerydto", "label": "ClaimQueryDto", "file_type": "code", "source_file": "D:\\Business\\Code\\SmartOPD\\smartopd-backend\\src\\nhcx\\dto\\nhcx.dto.ts", "source_location": "L82"}], "edges": [{"source": "d_business_code_smartopd_smartopd_backend_src_nhcx_dto_nhcx_dto_ts", "target": "class_validator", "relation": "imports_from", "confidence": "EXTRACTED", "source_file": "D:\\Business\\Code\\SmartOPD\\smartopd-backend\\src\\nhcx\\dto\\nhcx.dto.ts", "source_location": "L1", "weight": 1.0}, {"source": "d_business_code_smartopd_smartopd_backend_src_nhcx_dto_nhcx_dto_ts", "target": "swagger", "relation": "imports_from", "confidence": "EXTRACTED", "source_file": "D:\\Business\\Code\\SmartOPD\\smartopd-backend\\src\\nhcx\\dto\\nhcx.dto.ts", "source_location": "L10", "weight": 1.0}, {"source": "d_business_code_smartopd_smartopd_backend_src_nhcx_dto_nhcx_dto_ts", "target": "d_business_code_smartopd_smartopd_backend_src_nhcx_entities_nhcx_claim_record_entity", "relation": "imports_from", "confidence": "EXTRACTED", "source_file": "D:\\Business\\Code\\SmartOPD\\smartopd-backend\\src\\nhcx\\dto\\nhcx.dto.ts", "source_location": "L11", "weight": 1.0}, {"source": "d_business_code_smartopd_smartopd_backend_src_nhcx_dto_nhcx_dto_ts", "target": "nhcx_dto_createclaimdto", "relation": "contains", "confidence": "EXTRACTED", "source_file": "D:\\Business\\Code\\SmartOPD\\smartopd-backend\\src\\nhcx\\dto\\nhcx.dto.ts", "source_location": "L16", "weight": 1.0}, {"source": "d_business_code_smartopd_smartopd_backend_src_nhcx_dto_nhcx_dto_ts", "target": "nhcx_dto_updateclaimstatusdto", "relation": "contains", "confidence": "EXTRACTED", "source_file": "D:\\Business\\Code\\SmartOPD\\smartopd-backend\\src\\nhcx\\dto\\nhcx.dto.ts", "source_location": "L61", "weight": 1.0}, {"source": "d_business_code_smartopd_smartopd_backend_src_nhcx_dto_nhcx_dto_ts", "target": "nhcx_dto_claimquerydto", "relation": "contains", "confidence": "EXTRACTED", "source_file": "D:\\Business\\Code\\SmartOPD\\smartopd-backend\\src\\nhcx\\dto\\nhcx.dto.ts", "source_location": "L82", "weight": 1.0}], "raw_calls": []}